{
    "innings": [
        {
            "fow": [
                {
                    "over": 6.0, 
                    "score": 50, 
                    "name": "BJ Haddin", 
                    "wkt_nbr": 1
                }, 
                {
                    "over": 8.3, 
                    "score": 58, 
                    "name": "SR Watson", 
                    "wkt_nbr": 2
                }, 
                {
                    "over": 18.0, 
                    "score": 100, 
                    "name": "MJ Clarke", 
                    "wkt_nbr": 3
                }, 
                {
                    "over": 26.1, 
                    "score": 148, 
                    "name": "RT Ponting", 
                    "wkt_nbr": 4
                }, 
                {
                    "over": 34.1, 
                    "score": 172, 
                    "name": "CL White", 
                    "wkt_nbr": 5
                }, 
                {
                    "over": 46.5, 
                    "score": 244, 
                    "name": "JR Hopes", 
                    "wkt_nbr": 6
                }, 
                {
                    "over": 47.5, 
                    "score": 252, 
                    "name": "MEK Hussey", 
                    "wkt_nbr": 7
                }, 
                {
                    "over": 49.3, 
                    "score": 268, 
                    "name": "NM Hauritz", 
                    "wkt_nbr": 8
                }
            ], 
            "summary": {
                "runs": 275, 
                "bowlteam": "New Zealand", 
                "batteam": "Australia", 
                "wickets": 8, 
                "inning_no": 1, 
                "overs": 50
            }, 
            "batting": [
                {
                    "runs": 45, 
                    "balls": 31, 
                    "name": "SR Watson", 
                    "fours": 7, 
                    "six": 1, 
                    "dismissal": "caught PJ Ingram bowled JDP Oram"
                }, 
                {
                    "runs": 12, 
                    "balls": 16, 
                    "name": "BJ Haddin", 
                    "fours": 2, 
                    "six": 0, 
                    "dismissal": "bowled SE Bond"
                }, 
                {
                    "runs": 44, 
                    "balls": 56, 
                    "name": "RT Ponting", 
                    "fours": 4, 
                    "six": 0, 
                    "dismissal": "caught MJ Guptill bowled JEC Franklin"
                }, 
                {
                    "runs": 22, 
                    "balls": 31, 
                    "name": "MJ Clarke", 
                    "fours": 3, 
                    "six": 0, 
                    "dismissal": "caught BB McCullum bowled DR Tuffey"
                }, 
                {
                    "runs": 33, 
                    "balls": 49, 
                    "name": "CL White", 
                    "fours": 3, 
                    "six": 0, 
                    "dismissal": "bowled DR Tuffey"
                }, 
                {
                    "runs": 59, 
                    "balls": 59, 
                    "name": "MEK Hussey", 
                    "fours": 4, 
                    "six": 0, 
                    "dismissal": "bowled SE Bond"
                }, 
                {
                    "runs": 33, 
                    "balls": 42, 
                    "name": "JR Hopes", 
                    "fours": 2, 
                    "six": 0, 
                    "dismissal": "bowled TG Southee"
                }, 
                {
                    "runs": 21, 
                    "balls": 11, 
                    "name": "MG Johnson", 
                    "fours": 2, 
                    "six": 1, 
                    "dismissal": "not out"
                }, 
                {
                    "runs": 4, 
                    "balls": 5, 
                    "name": "NM Hauritz", 
                    "fours": 0, 
                    "six": 0, 
                    "dismissal": "caught NL McCullum (sub) bowled DR Tuffey"
                }, 
                {
                    "runs": 0, 
                    "balls": 0, 
                    "name": "RJ Harris", 
                    "fours": 0, 
                    "six": 0, 
                    "dismissal": "not out"
                }
            ], 
            "bowling": [
                {
                    "runs": 66, 
                    "overs": 8.0, 
                    "name": "TG Southee", 
                    "maiden": 0, 
                    "wickets": 1
                }, 
                {
                    "runs": 50, 
                    "overs": 10.0, 
                    "name": "SE Bond", 
                    "maiden": 1, 
                    "wickets": 2
                }, 
                {
                    "runs": 29, 
                    "overs": 7.0, 
                    "name": "JDP Oram", 
                    "maiden": 0, 
                    "wickets": 1
                }, 
                {
                    "runs": 58, 
                    "overs": 10.0, 
                    "name": "DR Tuffey", 
                    "maiden": 0, 
                    "wickets": 3
                }, 
                {
                    "runs": 44, 
                    "overs": 9.0, 
                    "name": "JEC Franklin", 
                    "maiden": 0, 
                    "wickets": 1
                }, 
                {
                    "runs": 27, 
                    "overs": 6.0, 
                    "name": "SB Styris", 
                    "maiden": 0, 
                    "wickets": 0
                }
            ]
        }, 
        {
            "fow": [
                {
                    "over": 11.2, 
                    "score": 75, 
                    "name": "PJ Ingram", 
                    "wkt_nbr": 1
                }, 
                {
                    "over": 15.0, 
                    "score": 90, 
                    "name": "BB McCullum", 
                    "wkt_nbr": 2
                }, 
                {
                    "over": 20.5, 
                    "score": 106, 
                    "name": "MJ Guptill", 
                    "wkt_nbr": 3
                }, 
                {
                    "over": 33.2, 
                    "score": 175, 
                    "name": "JEC Franklin", 
                    "wkt_nbr": 4
                }, 
                {
                    "over": 39.0, 
                    "score": 204, 
                    "name": "LRPL Taylor", 
                    "wkt_nbr": 5
                }, 
                {
                    "over": 41.1, 
                    "score": 207, 
                    "name": "NT Broom", 
                    "wkt_nbr": 6
                }, 
                {
                    "over": 45.0, 
                    "score": 234, 
                    "name": "DR Tuffey", 
                    "wkt_nbr": 7
                }, 
                {
                    "over": 46.2, 
                    "score": 246, 
                    "name": "TG Southee", 
                    "wkt_nbr": 8
                }
            ], 
            "summary": {
                "runs": 281, 
                "bowlteam": "Australia", 
                "batteam": "New Zealand", 
                "wickets": 8, 
                "inning_no": 2, 
                "overs": 49.2
            }, 
            "batting": [
                {
                    "runs": 45, 
                    "balls": 43, 
                    "name": "BB McCullum", 
                    "fours": 7, 
                    "six": 0, 
                    "dismissal": "bowled DE Bollinger"
                }, 
                {
                    "runs": 40, 
                    "balls": 41, 
                    "name": "PJ Ingram", 
                    "fours": 8, 
                    "six": 0, 
                    "dismissal": "caught MEK Hussey bowled MG Johnson"
                }, 
                {
                    "runs": 9, 
                    "balls": 30, 
                    "name": "MJ Guptill", 
                    "fours": 1, 
                    "six": 0, 
                    "dismissal": "caught SR Watson bowled JR Hopes"
                }, 
                {
                    "runs": 70, 
                    "balls": 71, 
                    "name": "LRPL Taylor", 
                    "fours": 6, 
                    "six": 1, 
                    "dismissal": "caught MEK Hussey bowled SR Watson"
                }, 
                {
                    "runs": 12, 
                    "balls": 31, 
                    "name": "JEC Franklin", 
                    "fours": 0, 
                    "six": 0, 
                    "dismissal": "caught BJ Haddin bowled NM Hauritz"
                }, 
                {
                    "runs": 19, 
                    "balls": 24, 
                    "name": "NT Broom", 
                    "fours": 1, 
                    "six": 1, 
                    "dismissal": "bowled DE Bollinger"
                }, 
                {
                    "runs": 49, 
                    "balls": 34, 
                    "name": "SB Styris", 
                    "fours": 7, 
                    "six": 1, 
                    "dismissal": "not out"
                }, 
                {
                    "runs": 12, 
                    "balls": 11, 
                    "name": "DR Tuffey", 
                    "fours": 0, 
                    "six": 0, 
                    "dismissal": "bowled RJ Harris"
                }, 
                {
                    "runs": 2, 
                    "balls": 3, 
                    "name": "TG Southee", 
                    "fours": 0, 
                    "six": 0, 
                    "dismissal": "run out CL White "
                }, 
                {
                    "runs": 11, 
                    "balls": 8, 
                    "name": "SE Bond", 
                    "fours": 2, 
                    "six": 0, 
                    "dismissal": "not out"
                }
            ], 
            "bowling": [
                {
                    "runs": 57, 
                    "overs": 10.0, 
                    "name": "RJ Harris", 
                    "maiden": 1, 
                    "wickets": 1
                }, 
                {
                    "runs": 58, 
                    "overs": 9.2, 
                    "name": "DE Bollinger", 
                    "maiden": 0, 
                    "wickets": 2
                }, 
                {
                    "runs": 46, 
                    "overs": 10.0, 
                    "name": "MG Johnson", 
                    "maiden": 1, 
                    "wickets": 1
                }, 
                {
                    "runs": 40, 
                    "overs": 6.0, 
                    "name": "JR Hopes", 
                    "maiden": 0, 
                    "wickets": 1
                }, 
                {
                    "runs": 47, 
                    "overs": 9.0, 
                    "name": "SR Watson", 
                    "maiden": 0, 
                    "wickets": 1
                }, 
                {
                    "runs": 8, 
                    "overs": 2.0, 
                    "name": "MJ Clarke", 
                    "maiden": 0, 
                    "wickets": 0
                }, 
                {
                    "runs": 15, 
                    "overs": 3.0, 
                    "name": "NM Hauritz", 
                    "maiden": 0, 
                    "wickets": 1
                }
            ]
        }
    ], 
    "matchinfo": {
        "city": "Napier", 
        "venue": "McLean Park", 
        "teams": "New Zealand vs Australia", 
        "mtype": "ODI", 
        "mom": "LRPL Taylor", 
        "date": "2010-03-03", 
        "id": "423791"
    }
}