{
    "innings": [
        {
            "fow": [
                {
                    "over": 3.1, 
                    "score": 22, 
                    "name": "MS Wade", 
                    "wkt_nbr": 1
                }, 
                {
                    "over": 4.3, 
                    "score": 26, 
                    "name": "RT Ponting", 
                    "wkt_nbr": 2
                }, 
                {
                    "over": 8.5, 
                    "score": 50, 
                    "name": "DA Warner", 
                    "wkt_nbr": 3
                }, 
                {
                    "over": 18.0, 
                    "score": 81, 
                    "name": "MEK Hussey", 
                    "wkt_nbr": 4
                }, 
                {
                    "over": 27.4, 
                    "score": 130, 
                    "name": "DJ Hussey", 
                    "wkt_nbr": 5
                }, 
                {
                    "over": 39.4, 
                    "score": 186, 
                    "name": "DT Christian", 
                    "wkt_nbr": 6
                }, 
                {
                    "over": 40.4, 
                    "score": 190, 
                    "name": "MJ Clarke", 
                    "wkt_nbr": 7
                }, 
                {
                    "over": 41.5, 
                    "score": 192, 
                    "name": "RJ Harris", 
                    "wkt_nbr": 8
                }, 
                {
                    "over": 48.0, 
                    "score": 224, 
                    "name": "MA Starc", 
                    "wkt_nbr": 9
                }, 
                {
                    "over": 49.1, 
                    "score": 231, 
                    "name": "CJ McKay", 
                    "wkt_nbr": 10
                }
            ], 
            "summary": {
                "runs": 231, 
                "bowlteam": "Sri Lanka", 
                "batteam": "Australia", 
                "wickets": 10, 
                "inning_no": 1, 
                "overs": 49.1
            }, 
            "batting": [
                {
                    "runs": 34, 
                    "balls": 29, 
                    "name": "DA Warner", 
                    "fours": 5, 
                    "six": 1, 
                    "dismissal": "bowled AD Mathews"
                }, 
                {
                    "runs": 1, 
                    "balls": 5, 
                    "name": "MS Wade", 
                    "fours": 0, 
                    "six": 0, 
                    "dismissal": "caught KC Sangakkara bowled KMDN Kulasekara"
                }, 
                {
                    "runs": 1, 
                    "balls": 4, 
                    "name": "RT Ponting", 
                    "fours": 0, 
                    "six": 0, 
                    "dismissal": "lbw bowled SL Malinga"
                }, 
                {
                    "runs": 57, 
                    "balls": 88, 
                    "name": "MJ Clarke", 
                    "fours": 4, 
                    "six": 0, 
                    "dismissal": "caught DPMD Jayawardene bowled AD Mathews"
                }, 
                {
                    "runs": 23, 
                    "balls": 32, 
                    "name": "MEK Hussey", 
                    "fours": 3, 
                    "six": 0, 
                    "dismissal": "caught and bowled bowled KMDN Kulasekara"
                }, 
                {
                    "runs": 27, 
                    "balls": 38, 
                    "name": "DJ Hussey", 
                    "fours": 2, 
                    "six": 1, 
                    "dismissal": "caught HDRL Thirimanne bowled SL Malinga"
                }, 
                {
                    "runs": 33, 
                    "balls": 44, 
                    "name": "DT Christian", 
                    "fours": 4, 
                    "six": 1, 
                    "dismissal": "stumped KC Sangakkara bowled SMSM Senanayake"
                }, 
                {
                    "runs": 3, 
                    "balls": 9, 
                    "name": "RJ Harris", 
                    "fours": 0, 
                    "six": 0, 
                    "dismissal": "caught KMDN Kulasekara bowled SMSM Senanayake"
                }, 
                {
                    "runs": 25, 
                    "balls": 25, 
                    "name": "CJ McKay", 
                    "fours": 3, 
                    "six": 0, 
                    "dismissal": "caught HDRL Thirimanne bowled KTGD Prasad"
                }, 
                {
                    "runs": 14, 
                    "balls": 19, 
                    "name": "MA Starc", 
                    "fours": 1, 
                    "six": 0, 
                    "dismissal": "caught WU Tharanga bowled KTGD Prasad"
                }, 
                {
                    "runs": 2, 
                    "balls": 2, 
                    "name": "XJ Doherty", 
                    "fours": 0, 
                    "six": 0, 
                    "dismissal": "not out"
                }
            ], 
            "bowling": [
                {
                    "runs": 48, 
                    "overs": 10.0, 
                    "name": "SL Malinga", 
                    "maiden": 0, 
                    "wickets": 2
                }, 
                {
                    "runs": 39, 
                    "overs": 10.0, 
                    "name": "KMDN Kulasekara", 
                    "maiden": 0, 
                    "wickets": 2
                }, 
                {
                    "runs": 37, 
                    "overs": 9.0, 
                    "name": "AD Mathews", 
                    "maiden": 0, 
                    "wickets": 2
                }, 
                {
                    "runs": 55, 
                    "overs": 9.1, 
                    "name": "KTGD Prasad", 
                    "maiden": 0, 
                    "wickets": 2
                }, 
                {
                    "runs": 45, 
                    "overs": 10.0, 
                    "name": "SMSM Senanayake", 
                    "maiden": 0, 
                    "wickets": 2
                }, 
                {
                    "runs": 1, 
                    "overs": 1.0, 
                    "name": "TM Dilshan", 
                    "maiden": 0, 
                    "wickets": 0
                }
            ]
        }, 
        {
            "fow": [
                {
                    "over": 3.3, 
                    "score": 11, 
                    "name": "WU Tharanga", 
                    "wkt_nbr": 1
                }, 
                {
                    "over": 14.3, 
                    "score": 61, 
                    "name": "KC Sangakkara", 
                    "wkt_nbr": 2
                }, 
                {
                    "over": 20.5, 
                    "score": 88, 
                    "name": "TM Dilshan", 
                    "wkt_nbr": 3
                }, 
                {
                    "over": 26.1, 
                    "score": 110, 
                    "name": "DPMD Jayawardene", 
                    "wkt_nbr": 4
                }, 
                {
                    "over": 27.4, 
                    "score": 119, 
                    "name": "HDRL Thirimanne", 
                    "wkt_nbr": 5
                }, 
                {
                    "over": 30.1, 
                    "score": 129, 
                    "name": "LD Chandimal", 
                    "wkt_nbr": 6
                }, 
                {
                    "over": 34.1, 
                    "score": 143, 
                    "name": "KMDN Kulasekara", 
                    "wkt_nbr": 7
                }, 
                {
                    "over": 42.0, 
                    "score": 175, 
                    "name": "SMSM Senanayake", 
                    "wkt_nbr": 8
                }, 
                {
                    "over": 44.2, 
                    "score": 180, 
                    "name": "SL Malinga", 
                    "wkt_nbr": 9
                }, 
                {
                    "over": 49.5, 
                    "score": 226, 
                    "name": "AD Mathews", 
                    "wkt_nbr": 10
                }
            ], 
            "summary": {
                "runs": 226, 
                "bowlteam": "Australia", 
                "batteam": "Sri Lanka", 
                "wickets": 10, 
                "inning_no": 2, 
                "overs": 49.5
            }, 
            "batting": [
                {
                    "runs": 5, 
                    "balls": 13, 
                    "name": "WU Tharanga", 
                    "fours": 1, 
                    "six": 0, 
                    "dismissal": "caught MJ Clarke bowled MA Starc"
                }, 
                {
                    "runs": 40, 
                    "balls": 57, 
                    "name": "TM Dilshan", 
                    "fours": 4, 
                    "six": 0, 
                    "dismissal": "caught MS Wade bowled RJ Harris"
                }, 
                {
                    "runs": 22, 
                    "balls": 32, 
                    "name": "KC Sangakkara", 
                    "fours": 3, 
                    "six": 0, 
                    "dismissal": "run out CJ McKay "
                }, 
                {
                    "runs": 37, 
                    "balls": 50, 
                    "name": "LD Chandimal", 
                    "fours": 4, 
                    "six": 0, 
                    "dismissal": "lbw bowled MJ Clarke"
                }, 
                {
                    "runs": 13, 
                    "balls": 13, 
                    "name": "DPMD Jayawardene", 
                    "fours": 1, 
                    "six": 0, 
                    "dismissal": "caught MS Wade bowled DT Christian"
                }, 
                {
                    "runs": 3, 
                    "balls": 6, 
                    "name": "HDRL Thirimanne", 
                    "fours": 0, 
                    "six": 0, 
                    "dismissal": "bowled XJ Doherty"
                }, 
                {
                    "runs": 64, 
                    "balls": 76, 
                    "name": "AD Mathews", 
                    "fours": 4, 
                    "six": 1, 
                    "dismissal": "caught DT Christian bowled MA Starc"
                }, 
                {
                    "runs": 8, 
                    "balls": 11, 
                    "name": "KMDN Kulasekara", 
                    "fours": 0, 
                    "six": 0, 
                    "dismissal": "caught MS Wade bowled DT Christian"
                }, 
                {
                    "runs": 9, 
                    "balls": 24, 
                    "name": "SMSM Senanayake", 
                    "fours": 0, 
                    "six": 0, 
                    "dismissal": "stumped MS Wade bowled XJ Doherty"
                }, 
                {
                    "runs": 1, 
                    "balls": 6, 
                    "name": "SL Malinga", 
                    "fours": 0, 
                    "six": 0, 
                    "dismissal": "caught MS Wade bowled CJ McKay"
                }, 
                {
                    "runs": 15, 
                    "balls": 11, 
                    "name": "KTGD Prasad", 
                    "fours": 1, 
                    "six": 0, 
                    "dismissal": "not out"
                }
            ], 
            "bowling": [
                {
                    "runs": 43, 
                    "overs": 10.0, 
                    "name": "RJ Harris", 
                    "maiden": 0, 
                    "wickets": 1
                }, 
                {
                    "runs": 50, 
                    "overs": 9.5, 
                    "name": "MA Starc", 
                    "maiden": 0, 
                    "wickets": 2
                }, 
                {
                    "runs": 50, 
                    "overs": 10.0, 
                    "name": "CJ McKay", 
                    "maiden": 0, 
                    "wickets": 1
                }, 
                {
                    "runs": 47, 
                    "overs": 8.0, 
                    "name": "DT Christian", 
                    "maiden": 1, 
                    "wickets": 2
                }, 
                {
                    "runs": 24, 
                    "overs": 10.0, 
                    "name": "XJ Doherty", 
                    "maiden": 0, 
                    "wickets": 2
                }, 
                {
                    "runs": 9, 
                    "overs": 2.0, 
                    "name": "MJ Clarke", 
                    "maiden": 0, 
                    "wickets": 1
                }
            ]
        }
    ], 
    "matchinfo": {
        "city": "Perth", 
        "venue": "Western Australia Cricket Association Ground", 
        "teams": "Australia vs Sri Lanka", 
        "mtype": "ODI", 
        "mom": "MJ Clarke", 
        "date": "2012-02-10", 
        "id": "518958"
    }
}