{
    "innings": [
        {
            "fow": [
                {
                    "over": 3.0, 
                    "score": 16, 
                    "name": "JJ Roy", 
                    "wkt_nbr": 1
                }, 
                {
                    "over": 5.3, 
                    "score": 42, 
                    "name": "JM Vince", 
                    "wkt_nbr": 2
                }, 
                {
                    "over": 5.4, 
                    "score": 42, 
                    "name": "EJG Morgan", 
                    "wkt_nbr": 3
                }, 
                {
                    "over": 6.0, 
                    "score": 42, 
                    "name": "JE Root", 
                    "wkt_nbr": 4
                }, 
                {
                    "over": 8.1, 
                    "score": 50, 
                    "name": "JC Buttler", 
                    "wkt_nbr": 5
                }, 
                {
                    "over": 9.2, 
                    "score": 57, 
                    "name": "BA Stokes", 
                    "wkt_nbr": 6
                }, 
                {
                    "over": 14.3, 
                    "score": 85, 
                    "name": "CJ Jordan", 
                    "wkt_nbr": 7
                }
            ], 
            "summary": {
                "runs": 142, 
                "bowlteam": "Afghanistan", 
                "batteam": "England", 
                "wickets": 7, 
                "inning_no": 1, 
                "overs": 20
            }, 
            "batting": [
                {
                    "runs": 5, 
                    "balls": 7, 
                    "name": "JJ Roy", 
                    "fours": 1, 
                    "six": 0, 
                    "dismissal": "bowled Amir Hamza"
                }, 
                {
                    "runs": 22, 
                    "balls": 18, 
                    "name": "JM Vince", 
                    "fours": 4, 
                    "six": 0, 
                    "dismissal": "caught and bowled bowled Mohammad Nabi"
                }, 
                {
                    "runs": 12, 
                    "balls": 8, 
                    "name": "JE Root", 
                    "fours": 1, 
                    "six": 1, 
                    "dismissal": "run out Rashid Khan "
                }, 
                {
                    "runs": 0, 
                    "balls": 1, 
                    "name": "EJG Morgan", 
                    "fours": 0, 
                    "six": 0, 
                    "dismissal": "bowled Mohammad Nabi"
                }, 
                {
                    "runs": 7, 
                    "balls": 8, 
                    "name": "BA Stokes", 
                    "fours": 1, 
                    "six": 0, 
                    "dismissal": "bowled Rashid Khan"
                }, 
                {
                    "runs": 6, 
                    "balls": 10, 
                    "name": "JC Buttler", 
                    "fours": 1, 
                    "six": 0, 
                    "dismissal": "caught Mohammad Nabi bowled Samiullah Shenwari"
                }, 
                {
                    "runs": 41, 
                    "balls": 33, 
                    "name": "MM Ali", 
                    "fours": 4, 
                    "six": 1, 
                    "dismissal": "not out"
                }, 
                {
                    "runs": 15, 
                    "balls": 18, 
                    "name": "CJ Jordan", 
                    "fours": 2, 
                    "six": 0, 
                    "dismissal": "caught and bowled bowled Rashid Khan"
                }, 
                {
                    "runs": 20, 
                    "balls": 17, 
                    "name": "DJ Willey", 
                    "fours": 0, 
                    "six": 2, 
                    "dismissal": "not out"
                }
            ], 
            "bowling": [
                {
                    "runs": 45, 
                    "overs": 4.0, 
                    "name": "Amir Hamza", 
                    "maiden": 0, 
                    "wickets": 1
                }, 
                {
                    "runs": 34, 
                    "overs": 4.0, 
                    "name": "Shapoor Zadran", 
                    "maiden": 0, 
                    "wickets": 0
                }, 
                {
                    "runs": 17, 
                    "overs": 4.0, 
                    "name": "Mohammad Nabi", 
                    "maiden": 0, 
                    "wickets": 2
                }, 
                {
                    "runs": 23, 
                    "overs": 4.0, 
                    "name": "Samiullah Shenwari", 
                    "maiden": 0, 
                    "wickets": 1
                }, 
                {
                    "runs": 17, 
                    "overs": 4.0, 
                    "name": "Rashid Khan", 
                    "maiden": 0, 
                    "wickets": 2
                }
            ]
        }, 
        {
            "fow": [
                {
                    "over": 0.3, 
                    "score": 4, 
                    "name": "Mohammad Shahzad", 
                    "wkt_nbr": 1
                }, 
                {
                    "over": 2.0, 
                    "score": 12, 
                    "name": "Asghar Stanikzai", 
                    "wkt_nbr": 2
                }, 
                {
                    "over": 3.0, 
                    "score": 13, 
                    "name": "Gulbadin Naib", 
                    "wkt_nbr": 3
                }, 
                {
                    "over": 7.5, 
                    "score": 35, 
                    "name": "Rashid Khan", 
                    "wkt_nbr": 4
                }, 
                {
                    "over": 8.5, 
                    "score": 39, 
                    "name": "Noor Ali Zadran", 
                    "wkt_nbr": 5
                }, 
                {
                    "over": 12.5, 
                    "score": 64, 
                    "name": "Mohammad Nabi", 
                    "wkt_nbr": 6
                }, 
                {
                    "over": 15.4, 
                    "score": 85, 
                    "name": "Najibullah Zadran", 
                    "wkt_nbr": 7
                }, 
                {
                    "over": 16.4, 
                    "score": 94, 
                    "name": "Samiullah Shenwari", 
                    "wkt_nbr": 8
                }, 
                {
                    "over": 18.1, 
                    "score": 108, 
                    "name": "Amir Hamza", 
                    "wkt_nbr": 9
                }
            ], 
            "summary": {
                "runs": 127, 
                "bowlteam": "England", 
                "batteam": "Afghanistan", 
                "wickets": 9, 
                "inning_no": 2, 
                "overs": 20
            }, 
            "batting": [
                {
                    "runs": 4, 
                    "balls": 3, 
                    "name": "Mohammad Shahzad", 
                    "fours": 1, 
                    "six": 0, 
                    "dismissal": "lbw bowled DJ Willey"
                }, 
                {
                    "runs": 17, 
                    "balls": 19, 
                    "name": "Noor Ali Zadran", 
                    "fours": 0, 
                    "six": 0, 
                    "dismissal": "caught and bowled bowled AU Rashid"
                }, 
                {
                    "runs": 1, 
                    "balls": 4, 
                    "name": "Asghar Stanikzai", 
                    "fours": 0, 
                    "six": 0, 
                    "dismissal": "caught JE Root bowled CJ Jordan"
                }, 
                {
                    "runs": 0, 
                    "balls": 5, 
                    "name": "Gulbadin Naib", 
                    "fours": 0, 
                    "six": 0, 
                    "dismissal": "caught BA Stokes bowled DJ Willey"
                }, 
                {
                    "runs": 15, 
                    "balls": 20, 
                    "name": "Rashid Khan", 
                    "fours": 1, 
                    "six": 1, 
                    "dismissal": "caught EJG Morgan bowled MM Ali"
                }, 
                {
                    "runs": 12, 
                    "balls": 10, 
                    "name": "Mohammad Nabi", 
                    "fours": 0, 
                    "six": 1, 
                    "dismissal": "caught CJ Jordan bowled AU Rashid"
                }, 
                {
                    "runs": 22, 
                    "balls": 27, 
                    "name": "Samiullah Shenwari", 
                    "fours": 1, 
                    "six": 0, 
                    "dismissal": "caught JE Root bowled BA Stokes"
                }, 
                {
                    "runs": 14, 
                    "balls": 10, 
                    "name": "Najibullah Zadran", 
                    "fours": 1, 
                    "six": 1, 
                    "dismissal": "run out CJ Jordan "
                }, 
                {
                    "runs": 35, 
                    "balls": 20, 
                    "name": "Shafiqullah", 
                    "fours": 4, 
                    "six": 2, 
                    "dismissal": "not out"
                }, 
                {
                    "runs": 1, 
                    "balls": 2, 
                    "name": "Amir Hamza", 
                    "fours": 0, 
                    "six": 0, 
                    "dismissal": "run out MM Ali "
                }, 
                {
                    "runs": 0, 
                    "balls": 0, 
                    "name": "Shapoor Zadran", 
                    "fours": 0, 
                    "six": 0, 
                    "dismissal": "not out"
                }
            ], 
            "bowling": [
                {
                    "runs": 23, 
                    "overs": 4.0, 
                    "name": "DJ Willey", 
                    "maiden": 0, 
                    "wickets": 2
                }, 
                {
                    "runs": 27, 
                    "overs": 4.0, 
                    "name": "CJ Jordan", 
                    "maiden": 0, 
                    "wickets": 1
                }, 
                {
                    "runs": 12, 
                    "overs": 4.0, 
                    "name": "LE Plunkett", 
                    "maiden": 1, 
                    "wickets": 0
                }, 
                {
                    "runs": 17, 
                    "overs": 2.0, 
                    "name": "MM Ali", 
                    "maiden": 0, 
                    "wickets": 1
                }, 
                {
                    "runs": 18, 
                    "overs": 3.0, 
                    "name": "AU Rashid", 
                    "maiden": 0, 
                    "wickets": 2
                }, 
                {
                    "runs": 28, 
                    "overs": 3.0, 
                    "name": "BA Stokes", 
                    "maiden": 0, 
                    "wickets": 1
                }
            ]
        }
    ], 
    "matchinfo": {
        "city": "Delhi", 
        "venue": "Feroz Shah Kotla", 
        "teams": "Afghanistan vs England", 
        "mtype": "T20", 
        "mom": "MM Ali", 
        "date": "2016-03-23", 
        "id": "951351"
    }
}