{
    "innings": [
        {
            "fow": [
                {
                    "over": 2.1, 
                    "score": 11, 
                    "name": "A Poulose", 
                    "wkt_nbr": 1
                }, 
                {
                    "over": 4.5, 
                    "score": 26, 
                    "name": "Zeeshan Maqsood", 
                    "wkt_nbr": 2
                }, 
                {
                    "over": 10.1, 
                    "score": 51, 
                    "name": "Khawar Ali", 
                    "wkt_nbr": 3
                }, 
                {
                    "over": 10.2, 
                    "score": 51, 
                    "name": "Aqib Ilyas", 
                    "wkt_nbr": 4
                }, 
                {
                    "over": 15.0, 
                    "score": 87, 
                    "name": "AV Lalcheta", 
                    "wkt_nbr": 5
                }, 
                {
                    "over": 15.2, 
                    "score": 88, 
                    "name": "Naseem Khushi", 
                    "wkt_nbr": 6
                }, 
                {
                    "over": 18.0, 
                    "score": 116, 
                    "name": "Khurram Nawaz", 
                    "wkt_nbr": 7
                }, 
                {
                    "over": 19.2, 
                    "score": 128, 
                    "name": "Mohammad Nadeem", 
                    "wkt_nbr": 8
                }, 
                {
                    "over": 19.3, 
                    "score": 128, 
                    "name": "Kaleemullah", 
                    "wkt_nbr": 9
                }, 
                {
                    "over": 20.0, 
                    "score": 133, 
                    "name": "Sultan Ahmed", 
                    "wkt_nbr": 10
                }
            ], 
            "summary": {
                "runs": 133, 
                "bowlteam": "Scotland", 
                "batteam": "Oman", 
                "wickets": 10, 
                "inning_no": 1, 
                "overs": 20
            }, 
            "batting": [
                {
                    "runs": 17, 
                    "balls": 22, 
                    "name": "Zeeshan Maqsood", 
                    "fours": 3, 
                    "six": 0, 
                    "dismissal": "caught CS MacLeod bowled MRJ Watt"
                }, 
                {
                    "runs": 0, 
                    "balls": 3, 
                    "name": "A Poulose", 
                    "fours": 0, 
                    "six": 0, 
                    "dismissal": "lbw bowled MRJ Watt"
                }, 
                {
                    "runs": 19, 
                    "balls": 21, 
                    "name": "Aqib Ilyas", 
                    "fours": 2, 
                    "six": 0, 
                    "dismissal": "run out RD Berrington "
                }, 
                {
                    "runs": 13, 
                    "balls": 16, 
                    "name": "Khawar Ali", 
                    "fours": 1, 
                    "six": 0, 
                    "dismissal": "bowled CD de Lange"
                }, 
                {
                    "runs": 23, 
                    "balls": 25, 
                    "name": "Khurram Nawaz", 
                    "fours": 2, 
                    "six": 1, 
                    "dismissal": "caught KJ Coetzer bowled SM Sharif"
                }, 
                {
                    "runs": 20, 
                    "balls": 14, 
                    "name": "AV Lalcheta", 
                    "fours": 2, 
                    "six": 1, 
                    "dismissal": "bowled MA Leask"
                }, 
                {
                    "runs": 0, 
                    "balls": 1, 
                    "name": "Naseem Khushi", 
                    "fours": 0, 
                    "six": 0, 
                    "dismissal": "lbw bowled CD de Lange"
                }, 
                {
                    "runs": 17, 
                    "balls": 13, 
                    "name": "Sultan Ahmed", 
                    "fours": 2, 
                    "six": 0, 
                    "dismissal": "run out MH Cross "
                }, 
                {
                    "runs": 2, 
                    "balls": 4, 
                    "name": "Mohammad Nadeem", 
                    "fours": 0, 
                    "six": 0, 
                    "dismissal": "bowled SM Sharif"
                }, 
                {
                    "runs": 0, 
                    "balls": 1, 
                    "name": "Kaleemullah", 
                    "fours": 0, 
                    "six": 0, 
                    "dismissal": "bowled SM Sharif"
                }, 
                {
                    "runs": 4, 
                    "balls": 2, 
                    "name": "Bilal Khan", 
                    "fours": 1, 
                    "six": 0, 
                    "dismissal": "not out"
                }
            ], 
            "bowling": [
                {
                    "runs": 21, 
                    "overs": 4.0, 
                    "name": "MA Leask", 
                    "maiden": 0, 
                    "wickets": 1
                }, 
                {
                    "runs": 33, 
                    "overs": 4.0, 
                    "name": "SM Sharif", 
                    "maiden": 0, 
                    "wickets": 3
                }, 
                {
                    "runs": 23, 
                    "overs": 4.0, 
                    "name": "MRJ Watt", 
                    "maiden": 0, 
                    "wickets": 2
                }, 
                {
                    "runs": 22, 
                    "overs": 4.0, 
                    "name": "CB Sole", 
                    "maiden": 0, 
                    "wickets": 0
                }, 
                {
                    "runs": 23, 
                    "overs": 4.0, 
                    "name": "CD de Lange", 
                    "maiden": 0, 
                    "wickets": 2
                }
            ]
        }, 
        {
            "fow": [
                {
                    "over": 6.3, 
                    "score": 43, 
                    "name": "KJ Coetzer", 
                    "wkt_nbr": 1
                }, 
                {
                    "over": 8.2, 
                    "score": 48, 
                    "name": "HG Munsey", 
                    "wkt_nbr": 2
                }, 
                {
                    "over": 17.0, 
                    "score": 119, 
                    "name": "MH Cross", 
                    "wkt_nbr": 3
                }
            ], 
            "summary": {
                "runs": 134, 
                "bowlteam": "Oman", 
                "batteam": "Scotland", 
                "wickets": 3, 
                "inning_no": 2, 
                "overs": 19
            }, 
            "batting": [
                {
                    "runs": 15, 
                    "balls": 19, 
                    "name": "HG Munsey", 
                    "fours": 1, 
                    "six": 0, 
                    "dismissal": "caught and bowled bowled Khawar Ali"
                }, 
                {
                    "runs": 25, 
                    "balls": 22, 
                    "name": "KJ Coetzer", 
                    "fours": 3, 
                    "six": 0, 
                    "dismissal": "lbw bowled Zeeshan Maqsood"
                }, 
                {
                    "runs": 47, 
                    "balls": 40, 
                    "name": "MH Cross", 
                    "fours": 3, 
                    "six": 2, 
                    "dismissal": "caught A Poulose bowled Bilal Khan"
                }, 
                {
                    "runs": 35, 
                    "balls": 30, 
                    "name": "CS MacLeod", 
                    "fours": 2, 
                    "six": 1, 
                    "dismissal": "not out"
                }, 
                {
                    "runs": 5, 
                    "balls": 4, 
                    "name": "CD Wallace", 
                    "fours": 0, 
                    "six": 0, 
                    "dismissal": "not out"
                }
            ], 
            "bowling": [
                {
                    "runs": 31, 
                    "overs": 3.0, 
                    "name": "Bilal Khan", 
                    "maiden": 0, 
                    "wickets": 1
                }, 
                {
                    "runs": 23, 
                    "overs": 4.0, 
                    "name": "AV Lalcheta", 
                    "maiden": 0, 
                    "wickets": 0
                }, 
                {
                    "runs": 22, 
                    "overs": 4.0, 
                    "name": "Zeeshan Maqsood", 
                    "maiden": 0, 
                    "wickets": 1
                }, 
                {
                    "runs": 14, 
                    "overs": 3.0, 
                    "name": "Kaleemullah", 
                    "maiden": 0, 
                    "wickets": 0
                }, 
                {
                    "runs": 28, 
                    "overs": 4.0, 
                    "name": "Khawar Ali", 
                    "maiden": 0, 
                    "wickets": 1
                }, 
                {
                    "runs": 13, 
                    "overs": 1.0, 
                    "name": "Mohammad Nadeem", 
                    "maiden": 0, 
                    "wickets": 0
                }
            ]
        }
    ], 
    "matchinfo": {
        "venue": "Dubai International Cricket Stadium", 
        "teams": "Oman vs Scotland", 
        "mtype": "T20", 
        "mom": "MH Cross", 
        "date": "2017-01-19", 
        "id": "1074968"
    }
}