{
    "innings": [
        {
            "fow": [
                {
                    "over": 1.3, 
                    "score": 9, 
                    "name": "ML Hayden", 
                    "wkt_nbr": 1
                }, 
                {
                    "over": 2.2, 
                    "score": 13, 
                    "name": "MS Dhoni", 
                    "wkt_nbr": 2
                }, 
                {
                    "over": 3.4, 
                    "score": 23, 
                    "name": "M Vijay", 
                    "wkt_nbr": 3
                }, 
                {
                    "over": 8.1, 
                    "score": 52, 
                    "name": "SK Raina", 
                    "wkt_nbr": 4
                }, 
                {
                    "over": 9.1, 
                    "score": 53, 
                    "name": "MEK Hussey", 
                    "wkt_nbr": 5
                }, 
                {
                    "over": 10.0, 
                    "score": 55, 
                    "name": "JA Morkel", 
                    "wkt_nbr": 6
                }, 
                {
                    "over": 14.1, 
                    "score": 72, 
                    "name": "R Ashwin", 
                    "wkt_nbr": 7
                }, 
                {
                    "over": 16.1, 
                    "score": 77, 
                    "name": "L Balaji", 
                    "wkt_nbr": 8
                }, 
                {
                    "over": 20.1, 
                    "score": 112, 
                    "name": "S Badrinath", 
                    "wkt_nbr": 9
                }
            ], 
            "summary": {
                "runs": 112, 
                "bowlteam": "Delhi Daredevils", 
                "batteam": "Chennai Super Kings", 
                "wickets": 9, 
                "inning_no": 1, 
                "overs": 20.1
            }, 
            "batting": [
                {
                    "runs": 17, 
                    "balls": 11, 
                    "name": "M Vijay", 
                    "fours": 3, 
                    "six": 0, 
                    "dismissal": "caught KD Karthik bowled A Nehra"
                }, 
                {
                    "runs": 1, 
                    "balls": 5, 
                    "name": "ML Hayden", 
                    "fours": 0, 
                    "six": 0, 
                    "dismissal": "caught PD Collingwood bowled A Nehra"
                }, 
                {
                    "runs": 0, 
                    "balls": 2, 
                    "name": "MS Dhoni", 
                    "fours": 0, 
                    "six": 0, 
                    "dismissal": "caught M Manhas bowled DP Nannes"
                }, 
                {
                    "runs": 15, 
                    "balls": 19, 
                    "name": "SK Raina", 
                    "fours": 2, 
                    "six": 0, 
                    "dismissal": "caught UT Yadav bowled TM Dilshan"
                }, 
                {
                    "runs": 15, 
                    "balls": 18, 
                    "name": "MEK Hussey", 
                    "fours": 2, 
                    "six": 0, 
                    "dismissal": "caught TM Dilshan bowled V Sehwag"
                }, 
                {
                    "runs": 30, 
                    "balls": 29, 
                    "name": "S Badrinath", 
                    "fours": 2, 
                    "six": 0, 
                    "dismissal": "caught DA Warner bowled A Nehra"
                }, 
                {
                    "runs": 1, 
                    "balls": 4, 
                    "name": "JA Morkel", 
                    "fours": 0, 
                    "six": 0, 
                    "dismissal": "caught PD Collingwood bowled V Sehwag"
                }, 
                {
                    "runs": 6, 
                    "balls": 13, 
                    "name": "R Ashwin", 
                    "fours": 0, 
                    "six": 0, 
                    "dismissal": "run out A Mishra "
                }, 
                {
                    "runs": 3, 
                    "balls": 8, 
                    "name": "L Balaji", 
                    "fours": 0, 
                    "six": 0, 
                    "dismissal": "lbw bowled A Mishra"
                }, 
                {
                    "runs": 16, 
                    "balls": 14, 
                    "name": "DE Bollinger", 
                    "fours": 1, 
                    "six": 1, 
                    "dismissal": "not out"
                }
            ], 
            "bowling": [
                {
                    "runs": 25, 
                    "overs": 3.1, 
                    "name": "DP Nannes", 
                    "maiden": 0, 
                    "wickets": 1
                }, 
                {
                    "runs": 26, 
                    "overs": 4.0, 
                    "name": "A Nehra", 
                    "maiden": 0, 
                    "wickets": 3
                }, 
                {
                    "runs": 11, 
                    "overs": 1.0, 
                    "name": "UT Yadav", 
                    "maiden": 0, 
                    "wickets": 0
                }, 
                {
                    "runs": 19, 
                    "overs": 4.0, 
                    "name": "TM Dilshan", 
                    "maiden": 0, 
                    "wickets": 1
                }, 
                {
                    "runs": 18, 
                    "overs": 4.0, 
                    "name": "V Sehwag", 
                    "maiden": 0, 
                    "wickets": 2
                }, 
                {
                    "runs": 13, 
                    "overs": 4.0, 
                    "name": "A Mishra", 
                    "maiden": 0, 
                    "wickets": 1
                }
            ]
        }, 
        {
            "fow": [
                {
                    "over": 0.3, 
                    "score": 1, 
                    "name": "DA Warner", 
                    "wkt_nbr": 1
                }, 
                {
                    "over": 1.1, 
                    "score": 5, 
                    "name": "V Sehwag", 
                    "wkt_nbr": 2
                }, 
                {
                    "over": 1.4, 
                    "score": 6, 
                    "name": "TM Dilshan", 
                    "wkt_nbr": 3
                }, 
                {
                    "over": 7.0, 
                    "score": 38, 
                    "name": "KD Karthik", 
                    "wkt_nbr": 4
                }
            ], 
            "summary": {
                "runs": 113, 
                "bowlteam": "Chennai Super Kings", 
                "batteam": "Delhi Daredevils", 
                "wickets": 4, 
                "inning_no": 2, 
                "overs": 18.4
            }, 
            "batting": [
                {
                    "runs": 4, 
                    "balls": 4, 
                    "name": "V Sehwag", 
                    "fours": 0, 
                    "six": 0, 
                    "dismissal": "caught ML Hayden bowled DE Bollinger"
                }, 
                {
                    "runs": 0, 
                    "balls": 2, 
                    "name": "DA Warner", 
                    "fours": 0, 
                    "six": 0, 
                    "dismissal": "caught M Vijay bowled R Ashwin"
                }, 
                {
                    "runs": 1, 
                    "balls": 2, 
                    "name": "TM Dilshan", 
                    "fours": 0, 
                    "six": 0, 
                    "dismissal": "bowled DE Bollinger"
                }, 
                {
                    "runs": 57, 
                    "balls": 56, 
                    "name": "G Gambhir", 
                    "fours": 5, 
                    "six": 0, 
                    "dismissal": "not out"
                }, 
                {
                    "runs": 13, 
                    "balls": 16, 
                    "name": "KD Karthik", 
                    "fours": 1, 
                    "six": 0, 
                    "dismissal": "caught S Badrinath bowled SB Jakati"
                }, 
                {
                    "runs": 25, 
                    "balls": 32, 
                    "name": "M Manhas", 
                    "fours": 2, 
                    "six": 0, 
                    "dismissal": "not out"
                }
            ], 
            "bowling": [
                {
                    "runs": 24, 
                    "overs": 4.0, 
                    "name": "R Ashwin", 
                    "maiden": 0, 
                    "wickets": 1
                }, 
                {
                    "runs": 24, 
                    "overs": 4.0, 
                    "name": "DE Bollinger", 
                    "maiden": 0, 
                    "wickets": 2
                }, 
                {
                    "runs": 14, 
                    "overs": 3.0, 
                    "name": "SB Jakati", 
                    "maiden": 0, 
                    "wickets": 1
                }, 
                {
                    "runs": 16, 
                    "overs": 2.4, 
                    "name": "JA Morkel", 
                    "maiden": 0, 
                    "wickets": 0
                }, 
                {
                    "runs": 16, 
                    "overs": 2.0, 
                    "name": "L Balaji", 
                    "maiden": 0, 
                    "wickets": 0
                }, 
                {
                    "runs": 15, 
                    "overs": 3.0, 
                    "name": "SK Raina", 
                    "maiden": 0, 
                    "wickets": 0
                }
            ]
        }
    ], 
    "matchinfo": {
        "city": "Chennai", 
        "venue": "MA Chidambaram Stadium, Chepauk", 
        "teams": "Chennai Super Kings vs Delhi Daredevils", 
        "mtype": "T20", 
        "mom": "G Gambhir", 
        "date": "2010-04-15", 
        "id": "419155"
    }
}