{
    "innings": [
        {
            "fow": [
                {
                    "over": 0.1, 
                    "score": 0, 
                    "name": "MA Agarwal", 
                    "wkt_nbr": 1
                }, 
                {
                    "over": 4.3, 
                    "score": 19, 
                    "name": "V Kohli", 
                    "wkt_nbr": 2
                }, 
                {
                    "over": 16.5, 
                    "score": 110, 
                    "name": "AB de Villiers", 
                    "wkt_nbr": 3
                }, 
                {
                    "over": 17.3, 
                    "score": 112, 
                    "name": "AUK Pathan", 
                    "wkt_nbr": 4
                }
            ], 
            "summary": {
                "runs": 140, 
                "bowlteam": "Mumbai Indians", 
                "batteam": "Royal Challengers Bangalore", 
                "wickets": 4, 
                "inning_no": 1, 
                "overs": 20
            }, 
            "batting": [
                {
                    "runs": 0, 
                    "balls": 1, 
                    "name": "MA Agarwal", 
                    "fours": 0, 
                    "six": 0, 
                    "dismissal": "bowled SL Malinga"
                }, 
                {
                    "runs": 59, 
                    "balls": 52, 
                    "name": "TM Dilshan", 
                    "fours": 4, 
                    "six": 2, 
                    "dismissal": "not out"
                }, 
                {
                    "runs": 12, 
                    "balls": 19, 
                    "name": "V Kohli", 
                    "fours": 2, 
                    "six": 0, 
                    "dismissal": "caught DJ Jacobs bowled KA Pollard"
                }, 
                {
                    "runs": 38, 
                    "balls": 36, 
                    "name": "AB de Villiers", 
                    "fours": 3, 
                    "six": 1, 
                    "dismissal": "caught and bowled bowled KA Pollard"
                }, 
                {
                    "runs": 0, 
                    "balls": 2, 
                    "name": "AUK Pathan", 
                    "fours": 0, 
                    "six": 0, 
                    "dismissal": "bowled SL Malinga"
                }, 
                {
                    "runs": 16, 
                    "balls": 10, 
                    "name": "SS Tiwary", 
                    "fours": 3, 
                    "six": 0, 
                    "dismissal": "not out"
                }
            ], 
            "bowling": [
                {
                    "runs": 32, 
                    "overs": 4.0, 
                    "name": "SL Malinga", 
                    "maiden": 0, 
                    "wickets": 2
                }, 
                {
                    "runs": 10, 
                    "overs": 3.0, 
                    "name": "MM Patel", 
                    "maiden": 0, 
                    "wickets": 0
                }, 
                {
                    "runs": 25, 
                    "overs": 4.0, 
                    "name": "KA Pollard", 
                    "maiden": 0, 
                    "wickets": 2
                }, 
                {
                    "runs": 26, 
                    "overs": 4.0, 
                    "name": "AG Murtaza", 
                    "maiden": 0, 
                    "wickets": 0
                }, 
                {
                    "runs": 27, 
                    "overs": 4.0, 
                    "name": "Harbhajan Singh", 
                    "maiden": 0, 
                    "wickets": 0
                }, 
                {
                    "runs": 9, 
                    "overs": 1.0, 
                    "name": "JEC Franklin", 
                    "maiden": 0, 
                    "wickets": 0
                }
            ]
        }, 
        {
            "fow": [
                {
                    "over": 4.2, 
                    "score": 33, 
                    "name": "DJ Jacobs", 
                    "wkt_nbr": 1
                }
            ], 
            "summary": {
                "runs": 143, 
                "bowlteam": "Royal Challengers Bangalore", 
                "batteam": "Mumbai Indians", 
                "wickets": 1, 
                "inning_no": 2, 
                "overs": 18.3
            }, 
            "batting": [
                {
                    "runs": 22, 
                    "balls": 16, 
                    "name": "DJ Jacobs", 
                    "fours": 2, 
                    "six": 2, 
                    "dismissal": "bowled DP Nannes"
                }, 
                {
                    "runs": 55, 
                    "balls": 46, 
                    "name": "SR Tendulkar", 
                    "fours": 7, 
                    "six": 0, 
                    "dismissal": "not out"
                }, 
                {
                    "runs": 63, 
                    "balls": 50, 
                    "name": "AT Rayudu", 
                    "fours": 9, 
                    "six": 0, 
                    "dismissal": "not out"
                }
            ], 
            "bowling": [
                {
                    "runs": 36, 
                    "overs": 4.0, 
                    "name": "Z Khan", 
                    "maiden": 0, 
                    "wickets": 0
                }, 
                {
                    "runs": 18, 
                    "overs": 4.0, 
                    "name": "DL Vettori", 
                    "maiden": 0, 
                    "wickets": 0
                }, 
                {
                    "runs": 0, 
                    "overs": 1.0, 
                    "name": "DP Nannes", 
                    "maiden": 1, 
                    "wickets": 1
                }, 
                {
                    "runs": 31, 
                    "overs": 3.0, 
                    "name": "A Mithun", 
                    "maiden": 0, 
                    "wickets": 0
                }, 
                {
                    "runs": 15, 
                    "overs": 2.0, 
                    "name": "V Kohli", 
                    "maiden": 0, 
                    "wickets": 0
                }, 
                {
                    "runs": 12, 
                    "overs": 1.0, 
                    "name": "TM Dilshan", 
                    "maiden": 0, 
                    "wickets": 0
                }, 
                {
                    "runs": 30, 
                    "overs": 3.3, 
                    "name": "AUK Pathan", 
                    "maiden": 0, 
                    "wickets": 0
                }
            ]
        }
    ], 
    "matchinfo": {
        "city": "Bangalore", 
        "venue": "M Chinnaswamy Stadium", 
        "teams": "Royal Challengers Bangalore vs Mumbai Indians", 
        "mtype": "T20", 
        "mom": "SR Tendulkar", 
        "date": "2011-04-12", 
        "id": "501205"
    }
}