{
    "innings": [
        {
            "fow": [
                {
                    "over": 6.3, 
                    "score": 51, 
                    "name": "M Vijay", 
                    "wkt_nbr": 1
                }, 
                {
                    "over": 10.5, 
                    "score": 96, 
                    "name": "SK Raina", 
                    "wkt_nbr": 2
                }, 
                {
                    "over": 16.3, 
                    "score": 147, 
                    "name": "MS Dhoni", 
                    "wkt_nbr": 3
                }, 
                {
                    "over": 19.1, 
                    "score": 176, 
                    "name": "JA Morkel", 
                    "wkt_nbr": 4
                }, 
                {
                    "over": 20.0, 
                    "score": 183, 
                    "name": "S Badrinath", 
                    "wkt_nbr": 5
                }
            ], 
            "summary": {
                "runs": 183, 
                "bowlteam": "Royal Challengers Bangalore", 
                "batteam": "Chennai Super Kings", 
                "wickets": 5, 
                "inning_no": 1, 
                "overs": 20
            }, 
            "batting": [
                {
                    "runs": 83, 
                    "balls": 56, 
                    "name": "MEK Hussey", 
                    "fours": 11, 
                    "six": 1, 
                    "dismissal": "not out"
                }, 
                {
                    "runs": 31, 
                    "balls": 21, 
                    "name": "M Vijay", 
                    "fours": 3, 
                    "six": 2, 
                    "dismissal": "caught Z Khan bowled R Ninan"
                }, 
                {
                    "runs": 29, 
                    "balls": 16, 
                    "name": "SK Raina", 
                    "fours": 3, 
                    "six": 1, 
                    "dismissal": "caught MA Agarwal bowled R Ninan"
                }, 
                {
                    "runs": 22, 
                    "balls": 16, 
                    "name": "MS Dhoni", 
                    "fours": 1, 
                    "six": 1, 
                    "dismissal": "caught AB de Villiers bowled Z Khan"
                }, 
                {
                    "runs": 9, 
                    "balls": 8, 
                    "name": "JA Morkel", 
                    "fours": 1, 
                    "six": 0, 
                    "dismissal": "caught MA Agarwal bowled JJ van der Wath"
                }, 
                {
                    "runs": 5, 
                    "balls": 3, 
                    "name": "S Badrinath", 
                    "fours": 1, 
                    "six": 0, 
                    "dismissal": "caught R Ninan bowled JJ van der Wath"
                }
            ], 
            "bowling": [
                {
                    "runs": 33, 
                    "overs": 4.0, 
                    "name": "Z Khan", 
                    "maiden": 0, 
                    "wickets": 1
                }, 
                {
                    "runs": 23, 
                    "overs": 4.0, 
                    "name": "DL Vettori", 
                    "maiden": 0, 
                    "wickets": 0
                }, 
                {
                    "runs": 49, 
                    "overs": 4.0, 
                    "name": "JJ van der Wath", 
                    "maiden": 0, 
                    "wickets": 2
                }, 
                {
                    "runs": 21, 
                    "overs": 2.0, 
                    "name": "TM Dilshan", 
                    "maiden": 0, 
                    "wickets": 0
                }, 
                {
                    "runs": 31, 
                    "overs": 3.0, 
                    "name": "R Ninan", 
                    "maiden": 0, 
                    "wickets": 2
                }, 
                {
                    "runs": 23, 
                    "overs": 3.0, 
                    "name": "V Kohli", 
                    "maiden": 0, 
                    "wickets": 0
                }
            ]
        }, 
        {
            "fow": [
                {
                    "over": 0.2, 
                    "score": 1, 
                    "name": "TM Dilshan", 
                    "wkt_nbr": 1
                }, 
                {
                    "over": 1.2, 
                    "score": 17, 
                    "name": "AUK Pathan", 
                    "wkt_nbr": 2
                }, 
                {
                    "over": 4.5, 
                    "score": 31, 
                    "name": "MA Agarwal", 
                    "wkt_nbr": 3
                }, 
                {
                    "over": 10.5, 
                    "score": 73, 
                    "name": "V Kohli", 
                    "wkt_nbr": 4
                }, 
                {
                    "over": 15.0, 
                    "score": 112, 
                    "name": "SS Tiwary", 
                    "wkt_nbr": 5
                }, 
                {
                    "over": 16.4, 
                    "score": 127, 
                    "name": "CA Pujara", 
                    "wkt_nbr": 6
                }, 
                {
                    "over": 18.2, 
                    "score": 145, 
                    "name": "AB de Villiers", 
                    "wkt_nbr": 7
                }
            ], 
            "summary": {
                "runs": 162, 
                "bowlteam": "Chennai Super Kings", 
                "batteam": "Royal Challengers Bangalore", 
                "wickets": 7, 
                "inning_no": 2, 
                "overs": 20
            }, 
            "batting": [
                {
                    "runs": 7, 
                    "balls": 13, 
                    "name": "MA Agarwal", 
                    "fours": 1, 
                    "six": 0, 
                    "dismissal": "caught JA Morkel bowled R Ashwin"
                }, 
                {
                    "runs": 0, 
                    "balls": 1, 
                    "name": "TM Dilshan", 
                    "fours": 0, 
                    "six": 0, 
                    "dismissal": "caught S Anirudha bowled JA Morkel"
                }, 
                {
                    "runs": 14, 
                    "balls": 5, 
                    "name": "AUK Pathan", 
                    "fours": 2, 
                    "six": 1, 
                    "dismissal": "bowled TG Southee"
                }, 
                {
                    "runs": 35, 
                    "balls": 28, 
                    "name": "V Kohli", 
                    "fours": 4, 
                    "six": 1, 
                    "dismissal": "caught S Anirudha bowled SB Jakati"
                }, 
                {
                    "runs": 65, 
                    "balls": 44, 
                    "name": "AB de Villiers", 
                    "fours": 5, 
                    "six": 2, 
                    "dismissal": "caught S Anirudha bowled JA Morkel"
                }, 
                {
                    "runs": 14, 
                    "balls": 13, 
                    "name": "SS Tiwary", 
                    "fours": 0, 
                    "six": 0, 
                    "dismissal": "caught MS Dhoni bowled S Randiv"
                }, 
                {
                    "runs": 2, 
                    "balls": 4, 
                    "name": "CA Pujara", 
                    "fours": 0, 
                    "six": 0, 
                    "dismissal": "caught M Vijay bowled S Randiv"
                }, 
                {
                    "runs": 14, 
                    "balls": 10, 
                    "name": "JJ van der Wath", 
                    "fours": 1, 
                    "six": 1, 
                    "dismissal": "not out"
                }, 
                {
                    "runs": 2, 
                    "balls": 2, 
                    "name": "DL Vettori", 
                    "fours": 0, 
                    "six": 0, 
                    "dismissal": "not out"
                }
            ], 
            "bowling": [
                {
                    "runs": 34, 
                    "overs": 4.0, 
                    "name": "JA Morkel", 
                    "maiden": 0, 
                    "wickets": 2
                }, 
                {
                    "runs": 32, 
                    "overs": 4.0, 
                    "name": "TG Southee", 
                    "maiden": 0, 
                    "wickets": 1
                }, 
                {
                    "runs": 23, 
                    "overs": 4.0, 
                    "name": "R Ashwin", 
                    "maiden": 0, 
                    "wickets": 1
                }, 
                {
                    "runs": 24, 
                    "overs": 4.0, 
                    "name": "S Randiv", 
                    "maiden": 0, 
                    "wickets": 2
                }, 
                {
                    "runs": 36, 
                    "overs": 3.0, 
                    "name": "SB Jakati", 
                    "maiden": 0, 
                    "wickets": 1
                }, 
                {
                    "runs": 10, 
                    "overs": 1.0, 
                    "name": "SK Raina", 
                    "maiden": 0, 
                    "wickets": 0
                }
            ]
        }
    ], 
    "matchinfo": {
        "city": "Chennai", 
        "venue": "MA Chidambaram Stadium, Chepauk", 
        "teams": "Chennai Super Kings vs Royal Challengers Bangalore", 
        "mtype": "T20", 
        "mom": "MEK Hussey", 
        "date": "2011-04-16", 
        "id": "501211"
    }
}