{
    "innings": [
        {
            "fow": [
                {
                    "over": 1.2, 
                    "score": 1, 
                    "name": "T Chetty", 
                    "wkt_nbr": 1
                }, 
                {
                    "over": 9.1, 
                    "score": 49, 
                    "name": "D van Niekerk", 
                    "wkt_nbr": 2
                }, 
                {
                    "over": 12.1, 
                    "score": 65, 
                    "name": "M du Preez", 
                    "wkt_nbr": 3
                }
            ], 
            "summary": {
                "runs": 119, 
                "bowlteam": "West Indies", 
                "batteam": "South Africa", 
                "wickets": 3, 
                "inning_no": 1, 
                "overs": 20
            }, 
            "batting": [
                {
                    "runs": 23, 
                    "balls": 26, 
                    "name": "D van Niekerk", 
                    "fours": 3, 
                    "six": 0, 
                    "dismissal": "bowled SR Taylor"
                }, 
                {
                    "runs": 0, 
                    "balls": 2, 
                    "name": "T Chetty", 
                    "fours": 0, 
                    "six": 0, 
                    "dismissal": "caught HK Matthews bowled SS Connell"
                }, 
                {
                    "runs": 32, 
                    "balls": 37, 
                    "name": "M du Preez", 
                    "fours": 3, 
                    "six": 0, 
                    "dismissal": "caught SACA King bowled A Mohammed"
                }, 
                {
                    "runs": 24, 
                    "balls": 35, 
                    "name": "M Kapp", 
                    "fours": 1, 
                    "six": 0, 
                    "dismissal": "not out"
                }, 
                {
                    "runs": 33, 
                    "balls": 23, 
                    "name": "L Lee", 
                    "fours": 1, 
                    "six": 2, 
                    "dismissal": "not out"
                }
            ], 
            "bowling": [
                {
                    "runs": 25, 
                    "overs": 4.0, 
                    "name": "TD Smartt", 
                    "maiden": 0, 
                    "wickets": 0
                }, 
                {
                    "runs": 14, 
                    "overs": 3.0, 
                    "name": "SS Connell", 
                    "maiden": 0, 
                    "wickets": 1
                }, 
                {
                    "runs": 22, 
                    "overs": 4.0, 
                    "name": "A Mohammed", 
                    "maiden": 0, 
                    "wickets": 1
                }, 
                {
                    "runs": 23, 
                    "overs": 4.0, 
                    "name": "SR Taylor", 
                    "maiden": 0, 
                    "wickets": 1
                }, 
                {
                    "runs": 22, 
                    "overs": 3.0, 
                    "name": "HK Matthews", 
                    "maiden": 0, 
                    "wickets": 0
                }, 
                {
                    "runs": 12, 
                    "overs": 2.0, 
                    "name": "SL Quintyne", 
                    "maiden": 0, 
                    "wickets": 0
                }
            ]
        }, 
        {
            "fow": [
                {
                    "over": 2.5, 
                    "score": 15, 
                    "name": "Kycia A Knight", 
                    "wkt_nbr": 1
                }, 
                {
                    "over": 8.3, 
                    "score": 47, 
                    "name": "HK Matthews", 
                    "wkt_nbr": 2
                }, 
                {
                    "over": 11.1, 
                    "score": 57, 
                    "name": "SR Taylor", 
                    "wkt_nbr": 3
                }, 
                {
                    "over": 14.2, 
                    "score": 81, 
                    "name": "DJS Dottin", 
                    "wkt_nbr": 4
                }, 
                {
                    "over": 15.1, 
                    "score": 85, 
                    "name": "Kyshona A Knight", 
                    "wkt_nbr": 5
                }, 
                {
                    "over": 15.5, 
                    "score": 87, 
                    "name": "SA Campbelle", 
                    "wkt_nbr": 6
                }, 
                {
                    "over": 17.1, 
                    "score": 97, 
                    "name": "SL Quintyne", 
                    "wkt_nbr": 7
                }, 
                {
                    "over": 17.2, 
                    "score": 97, 
                    "name": "SACA King", 
                    "wkt_nbr": 8
                }
            ], 
            "summary": {
                "runs": 115, 
                "bowlteam": "South Africa", 
                "batteam": "West Indies", 
                "wickets": 8, 
                "inning_no": 2, 
                "overs": 20
            }, 
            "batting": [
                {
                    "runs": 3, 
                    "balls": 10, 
                    "name": "Kycia A Knight", 
                    "fours": 0, 
                    "six": 0, 
                    "dismissal": "lbw bowled M Daniels"
                }, 
                {
                    "runs": 24, 
                    "balls": 26, 
                    "name": "HK Matthews", 
                    "fours": 3, 
                    "six": 0, 
                    "dismissal": "caught M Daniels bowled Y Fourie"
                }, 
                {
                    "runs": 21, 
                    "balls": 24, 
                    "name": "SR Taylor", 
                    "fours": 3, 
                    "six": 0, 
                    "dismissal": "bowled D van Niekerk"
                }, 
                {
                    "runs": 24, 
                    "balls": 18, 
                    "name": "DJS Dottin", 
                    "fours": 1, 
                    "six": 2, 
                    "dismissal": "caught L Lee bowled M Klaas"
                }, 
                {
                    "runs": 9, 
                    "balls": 12, 
                    "name": "Kyshona A Knight", 
                    "fours": 0, 
                    "six": 0, 
                    "dismissal": "caught S Luus bowled Y Fourie"
                }, 
                {
                    "runs": 6, 
                    "balls": 7, 
                    "name": "SACA King", 
                    "fours": 0, 
                    "six": 0, 
                    "dismissal": "caught and bowled bowled S Ismail"
                }, 
                {
                    "runs": 1, 
                    "balls": 2, 
                    "name": "SA Campbelle", 
                    "fours": 0, 
                    "six": 0, 
                    "dismissal": "run out D van Niekerk "
                }, 
                {
                    "runs": 5, 
                    "balls": 5, 
                    "name": "SL Quintyne", 
                    "fours": 0, 
                    "six": 0, 
                    "dismissal": "run out L Lee "
                }, 
                {
                    "runs": 5, 
                    "balls": 7, 
                    "name": "A Mohammed", 
                    "fours": 0, 
                    "six": 0, 
                    "dismissal": "not out"
                }, 
                {
                    "runs": 13, 
                    "balls": 9, 
                    "name": "SS Connell", 
                    "fours": 1, 
                    "six": 0, 
                    "dismissal": "not out"
                }
            ], 
            "bowling": [
                {
                    "runs": 20, 
                    "overs": 4.0, 
                    "name": "Y Fourie", 
                    "maiden": 0, 
                    "wickets": 2
                }, 
                {
                    "runs": 22, 
                    "overs": 4.0, 
                    "name": "S Ismail", 
                    "maiden": 0, 
                    "wickets": 1
                }, 
                {
                    "runs": 21, 
                    "overs": 4.0, 
                    "name": "M Daniels", 
                    "maiden": 0, 
                    "wickets": 1
                }, 
                {
                    "runs": 22, 
                    "overs": 3.0, 
                    "name": "M Klaas", 
                    "maiden": 0, 
                    "wickets": 1
                }, 
                {
                    "runs": 16, 
                    "overs": 4.0, 
                    "name": "D van Niekerk", 
                    "maiden": 0, 
                    "wickets": 1
                }, 
                {
                    "runs": 13, 
                    "overs": 1.0, 
                    "name": "S Luus", 
                    "maiden": 0, 
                    "wickets": 0
                }
            ]
        }
    ], 
    "matchinfo": {
        "city": "Cape Town", 
        "venue": "Newlands", 
        "teams": "South Africa vs West Indies", 
        "mtype": "T20", 
        "mom": "L Lee", 
        "date": "2016-03-09", 
        "id": "907399"
    }
}